static/__init__.py
static/bundle.js
static/index.html
wspr/__init__.py
wspr/emulator.py
wspr/monitor.py
wspr/router.py
wspr/server.py
wspr/upgrade.py
wspr/web_endpoints.py
wspr/websocket_endpoints.py
wspr/wire_format.py
wspr_server-0.1.14.dist-info/METADATA
wspr_server-0.1.14.dist-info/RECORD
wspr_server-0.1.14.dist-info/WHEEL
wspr_server-0.1.14.dist-info/entry_points.txt
wspr_server-0.1.14.dist-info/top_level.txt
