Metadata-Version: 2.1
Name: wspr-server
Version: 0.1.14
Summary: UNKNOWN
Home-page: https://github.com/wsprpi/wspr-software
Author: Michael Rawson
Author-email: michael@rawsons.uk
License: UNKNOWN
Platform: UNKNOWN
Requires-Dist: tornado (>=4.5)
Requires-Dist: pyserial (>=3.4)
Requires-Dist: RPi.GPIO (>=0.6)
